skinsegmenter/SkinDetection.py
skinsegmenter/__init__.py
skinsegmenter-1.2.dist-info/METADATA
skinsegmenter-1.2.dist-info/WHEEL
skinsegmenter-1.2.dist-info/top_level.txt
skinsegmenter-1.2.dist-info/RECORD
