Metadata-Version: 2.1
Name: skinsegmenter
Version: 1.2
Requires-Dist: ultralytics
Requires-Dist: gdown
